nasap/__init__.py
nasap/__version__.py
nasap/batch_nasap.py
nasap/nasap.py
nasap/scripts/extract_preprocess.py
nasap/scripts/feature_attrs.py
nasap/scripts/genome_track_visualization.py
nasap/scripts/map1.bash
nasap/scripts/map2.bash
nasap/scripts/map_split.py
nasap/scripts/network_analysis.py
nasap/scripts/parse_gtf.py
nasap/scripts/pausing_sites.py
nasap/scripts/pausing_sites_low_memory.py
nasap/scripts/plot.py
nasap/scripts/preprocess.bash
nasap/scripts/preprocess_fast.bash
nasap/scripts/py_ext.py
nasap/scripts/render_template.py
nasap/scripts/tmp_plot.py
nasap/scripts/x.py
nasap/scripts/gencore/gencore
nasap/scripts/templates/template.html
nasap/scripts/templates/template_track.txt
nasap/scripts/templates/static/vue.min.js
nasap/scripts/ucsc/bedGraphToBigWig
nasap-0.2.10.data/data/bedGraphToBigWig
nasap-0.2.10.data/data/gencore
nasap-0.2.10.data/data/nasap/scripts/extract_preprocess.py
nasap-0.2.10.data/data/nasap/scripts/feature_attrs.py
nasap-0.2.10.data/data/nasap/scripts/genome_track_visualization.py
nasap-0.2.10.data/data/nasap/scripts/map1.bash
nasap-0.2.10.data/data/nasap/scripts/map2.bash
nasap-0.2.10.data/data/nasap/scripts/map_split.py
nasap-0.2.10.data/data/nasap/scripts/network_analysis.py
nasap-0.2.10.data/data/nasap/scripts/parse_gtf.py
nasap-0.2.10.data/data/nasap/scripts/pausing_sites.py
nasap-0.2.10.data/data/nasap/scripts/pausing_sites_low_memory.py
nasap-0.2.10.data/data/nasap/scripts/plot.py
nasap-0.2.10.data/data/nasap/scripts/preprocess.bash
nasap-0.2.10.data/data/nasap/scripts/preprocess_fast.bash
nasap-0.2.10.data/data/nasap/scripts/py_ext.py
nasap-0.2.10.data/data/nasap/scripts/render_template.py
nasap-0.2.10.data/data/nasap/scripts/tmp_plot.py
nasap-0.2.10.data/data/nasap/scripts/x.py
nasap-0.2.10.data/data/nasap/scripts/templates/template.html
nasap-0.2.10.data/data/nasap/scripts/templates/template_track.txt
nasap-0.2.10.data/data/nasap/scripts/templates/static/vue.min.js
nasap-0.2.10.dist-info/METADATA
nasap-0.2.10.dist-info/WHEEL
nasap-0.2.10.dist-info/entry_points.txt
nasap-0.2.10.dist-info/top_level.txt
nasap-0.2.10.dist-info/RECORD
