Metadata-Version: 2.1
Name: nasap
Version: 0.2.10
Summary: This is nASAP setup file
Home-page: https://github.com/biodancerwanghzi/nasap/
Author: biodancer
Author-email: szxszx@foxmail.com
License: UNKNOWN
Platform: UNKNOWN
Classifier: Programming Language :: Python :: 3
Classifier: License :: OSI Approved :: MIT License
Classifier: Operating System :: OS Independent
Requires-Dist: fire
Requires-Dist: psutil
Requires-Dist: loguru
Requires-Dist: numpy
Requires-Dist: scipy
Requires-Dist: pyBigWig
Requires-Dist: matplotlib
Requires-Dist: seaborn
Requires-Dist: hvplot
Requires-Dist: networkx
Requires-Dist: python-louvain
Provides-Extra: genomebrowser
Requires-Dist: pyGenomeTrack ; extra == 'genomebrowser'
